xcom_proto/XcomAbs.py
xcom_proto/XcomLAN.py
xcom_proto/XcomRS232.py
xcom_proto/__init__.py
xcom_proto/parameters.py
xcom_proto/protocol.py
xcom_proto-0.3.7.dist-info/LICENSE
xcom_proto-0.3.7.dist-info/METADATA
xcom_proto-0.3.7.dist-info/WHEEL
xcom_proto-0.3.7.dist-info/RECORD
