Metadata-Version: 2.1
Name: xcom_proto
Version: 0.3.7
Summary: Python library implementing Studer-Innotec Xcom protocol used by Xcom-232i and Xcom-LAN
Home-page: https://github.com/zocker-160/xcom-protocol
License: GPL-3.0-or-later
Author: zocker_160
Author-email: zocker1600@posteo.net
Requires-Python: >=3.9,<4.0
Classifier: License :: OSI Approved :: GNU General Public License v3 or later (GPLv3+)
Classifier: Programming Language :: Python :: 3
Classifier: Programming Language :: Python :: 3.9
Classifier: Programming Language :: Python :: 3.10
Classifier: Programming Language :: Python :: 3.11
Classifier: Programming Language :: Python :: 3.12
Requires-Dist: pyserial (>=3.5,<4.0)
Project-URL: Repository, https://github.com/zocker-160/xcom-protocol
